odoo/addons/stock_account_valuation_report/README.rst
odoo/addons/stock_account_valuation_report/__init__.py
odoo/addons/stock_account_valuation_report/__manifest__.py
odoo/addons/stock_account_valuation_report/i18n/stock_account_valuation_report.pot
odoo/addons/stock_account_valuation_report/models/__init__.py
odoo/addons/stock_account_valuation_report/models/account_move_line.py
odoo/addons/stock_account_valuation_report/models/product_product.py
odoo/addons/stock_account_valuation_report/readme/CONTRIBUTORS.rst
odoo/addons/stock_account_valuation_report/readme/DESCRIPTION.rst
odoo/addons/stock_account_valuation_report/static/description/icon.png
odoo/addons/stock_account_valuation_report/static/description/index.html
odoo/addons/stock_account_valuation_report/views/product_product_views.xml
odoo/addons/stock_account_valuation_report/wizards/__init__.py
odoo/addons/stock_account_valuation_report/wizards/stock_quantity_history.py
odoo11_addon_stock_account_valuation_report-11.0.1.0.0.99.dev3.dist-info/METADATA
odoo11_addon_stock_account_valuation_report-11.0.1.0.0.99.dev3.dist-info/WHEEL
odoo11_addon_stock_account_valuation_report-11.0.1.0.0.99.dev3.dist-info/top_level.txt
odoo11_addon_stock_account_valuation_report-11.0.1.0.0.99.dev3.dist-info/RECORD
